hotfuzz_control_panel/__main__.py
hotfuzz_control_panel-0.4.0.dist-info/WHEEL
hotfuzz_control_panel-0.4.0.dist-info/METADATA
hotfuzz_control_panel-0.4.0.dist-info/RECORD
